geoClassy/__init__.py
geoClassy/single.py
geoClassy-0.1.1.dist-info/METADATA
geoClassy-0.1.1.dist-info/WHEEL
geoClassy-0.1.1.dist-info/top_level.txt
geoClassy-0.1.1.dist-info/RECORD
