Metadata-Version: 2.1
Name: geoClassy
Version: 0.1.1
Summary: a classificator of GPS point over geoJson areas
Home-page: https://www.simboli.eu/
Author: Nicola Simboli
Author-email: support@simboli.eu
License: MIT
Keywords: geoJson,Open Street Map,gps,shapely
